LICENSE.txt
MANIFEST.in
README.md
setup.cfg
setup.py
tika/__init__.py
tika/config.py
tika/detector.py
tika/language.py
tika/parser.py
tika/tika.py
tika/translate.py
tika/unpack.py
tika.egg-info/PKG-INFO
tika.egg-info/SOURCES.txt
tika.egg-info/dependency_links.txt
tika.egg-info/entry_points.txt
tika.egg-info/requires.txt
tika.egg-info/top_level.txt
tika.egg-info/zip-safe
tika/tests/__init__.py
tika/tests/test_tika.py
tika/tests/tests_params.py