Metadata-Version: 1.1
Name: tika
Version: 1.16
Summary: Apache Tika Python library
Home-page: http://github.com/chrismattmann/tika-python
Author: Chris Mattmann
Author-email: chris.a.mttmnn@nasa.gov
License: 
